pygame_gridcalculator/__init__.py
pygame_gridcalculator/gridcalculator.py
pygame_gridcalculator/shapefactory.py
pygame_gridcalculator-2.1.0.dist-info/LICENSE
pygame_gridcalculator-2.1.0.dist-info/METADATA
pygame_gridcalculator-2.1.0.dist-info/WHEEL
pygame_gridcalculator-2.1.0.dist-info/top_level.txt
pygame_gridcalculator-2.1.0.dist-info/RECORD
