Metadata-Version: 2.1
Name: pygame-gridcalculator
Version: 2.1.0
Summary: For generating a virtual grid to map pixels against and generate shapes from for a pygame display.
Home-page: https://github.com/davethepunkyone/pygame-gridcalculator
Author: Dave Harding
Author-email: dave@punkamania.org
Classifier: Programming Language :: Python :: 3
Classifier: License :: OSI Approved :: MIT License
Classifier: Operating System :: OS Independent
Classifier: Topic :: Software Development :: Libraries :: pygame
Classifier: Development Status :: 5 - Production/Stable
Requires-Python: >=3.10
License-File: LICENSE
Requires-Dist: pygame>=2.6
